evo/data_converters/common/__init__.py
evo/data_converters/common/blockmodel_client.py
evo/data_converters/common/crs.py
evo/data_converters/common/evo_client.py
evo/data_converters/common/exceptions.py
evo/data_converters/common/generate_paths.py
evo/data_converters/common/grid_data.py
evo/data_converters/common/hexahedrons.py
evo/data_converters/common/publish.py
evo/data_converters/common/test_tools.py
evo/data_converters/common/utils.py
evo_data_converters_common-0.3.1.dist-info/METADATA
evo_data_converters_common-0.3.1.dist-info/WHEEL
evo_data_converters_common-0.3.1.dist-info/licenses/LICENSE.md
evo_data_converters_common-0.3.1.dist-info/RECORD
