Metadata-Version: 2.4
Name: evo-data-converters-common
Version: 0.3.1
Summary: Python framework for building data converters between common geoscience data formats
Project-URL: Source, https://github.com/SeequentEvo/evo-python-sdk
Project-URL: Tracker, https://github.com/SeequentEvo/evo-python-sdk/issues
Project-URL: Homepage, https://www.seequent.com/
Project-URL: Documentation, https://developer.seequent.com/
Author-email: Seequent <support@seequent.com>
License-File: LICENSE.md
Requires-Python: >=3.10
Requires-Dist: aiohttp
Requires-Dist: evo-objects>=0.3.0
Requires-Dist: evo-schemas>=2025.9.12
Requires-Dist: evo-sdk-common>=0.4.2
Requires-Dist: nest-asyncio
Requires-Dist: numpy==1.26.3
Requires-Dist: pyarrow
Requires-Dist: pyproj>=3.7.1
Requires-Dist: requests
Requires-Dist: scipy
